{
	"configurations" : 
	[
		{
			"directories" : 
			[
				{
					"build" : ".",
					"minimumCMakeVersion" : 
					{
						"string" : "3.12"
					},
					"projectIndex" : 0,
					"source" : ".",
					"targetIndexes" : 
					[
						0
					]
				}
			],
			"name" : "Debug",
			"projects" : 
			[
				{
					"directoryIndexes" : 
					[
						0
					],
					"name" : "Renderer",
					"targetIndexes" : 
					[
						0
					]
				}
			],
			"targets" : 
			[
				{
					"directoryIndex" : 0,
					"id" : "Renderer::@6890427a1f51a3e7e1df",
					"jsonFile" : "target-Renderer-Debug-749afd691370d7ca8151.json",
					"name" : "Renderer",
					"projectIndex" : 0
				}
			]
		}
	],
	"kind" : "codemodel",
	"paths" : 
	{
		"build" : "C:/Uni/Year 3/Computer Graphics/project final/Render/out/build/x64-Debug",
		"source" : "C:/Uni/Year 3/Computer Graphics/project final/Render"
	},
	"version" : 
	{
		"major" : 2,
		"minor" : 2
	}
}
